azure_ai_search_plugin/__init__.py
azure_ai_search_plugin/cosmos_data_retriever.py
azure_ai_search_plugin/exceptions.py
azure_ai_search_plugin/main.py
azure_ai_search_plugin/utils/__init__.py
azure_ai_search_plugin/utils/logger.py
azure_ai_search_plugin-0.2.4.dist-info/METADATA
azure_ai_search_plugin-0.2.4.dist-info/WHEEL
azure_ai_search_plugin-0.2.4.dist-info/top_level.txt
azure_ai_search_plugin-0.2.4.dist-info/RECORD
