Metadata-Version: 2.4
Name: azure_ai_search_plugin
Version: 0.2.4
Summary: Reusable Azure Cognitive Search plugin for Semantic Kernel
Home-page: https://github.com/Ranjanisiva36/Azure_ai_search
Author: Sivaranjani
Author-email: Sivaranjani Palanivel <sivaranjani.palanivel@nihilent.com>
License: MIT
Project-URL: Homepage, https://github.com/Ranjanisiva36/Azure_ai_search
Project-URL: Documentation, https://github.com/Ranjanisiva36/Azure_ai_search/blob/main/README.md
Project-URL: Repository, https://github.com/Ranjanisiva36/Azure_ai_search
Keywords: azure,cognitive-search,semantic-kernel,plugin
Classifier: Programming Language :: Python :: 3
Classifier: License :: OSI Approved :: MIT License
Classifier: Operating System :: OS Independent
Classifier: Development Status :: 4 - Beta
Classifier: Intended Audience :: Developers
Classifier: Topic :: Software Development :: Libraries :: Python Modules
Requires-Python: >=3.8
Requires-Dist: azure-search-documents>=11.6.0
Requires-Dist: azure-core>=1.30.0
Requires-Dist: semantic-kernel>=0.9.0
Provides-Extra: dev
Requires-Dist: pytest>=8.0; extra == "dev"
Requires-Dist: pytest-asyncio>=0.23.0; extra == "dev"
Requires-Dist: flake8>=7.0; extra == "dev"
Requires-Dist: black>=24.0; extra == "dev"
Requires-Dist: mypy>=1.8.0; extra == "dev"
Provides-Extra: docs
Requires-Dist: mkdocs>=1.5.0; extra == "docs"
Requires-Dist: mkdocs-material>=9.5.0; extra == "docs"
Provides-Extra: examples
Requires-Dist: python-dotenv>=1.0.0; extra == "examples"
Requires-Dist: ipython>=8.0.0; extra == "examples"
